unitcellengine/__init__.py
unitcellengine/design.py
unitcellengine/utilities.py
unitcellengine/analysis/__init__.py
unitcellengine/analysis/homogenization.py
unitcellengine/analysis/internal.py
unitcellengine/analysis/material.py
unitcellengine/analysis/multiprocess.py
unitcellengine/geometry/__init__.py
unitcellengine/geometry/gmsh.py
unitcellengine/geometry/sdf.py
unitcellengine/geometry/definitions/Body centered cubic foam.ltcx
unitcellengine/geometry/definitions/Body centered cubic.ltcx
unitcellengine/geometry/definitions/Column.ltcx
unitcellengine/geometry/definitions/Columns.ltcx
unitcellengine/geometry/definitions/Diamond.ltcx
unitcellengine/geometry/definitions/Face centered cubic foam.ltcx
unitcellengine/geometry/definitions/Face centered cubic.ltcx
unitcellengine/geometry/definitions/Fluorite.ltcx
unitcellengine/geometry/definitions/Hex prism central axis edge.ltcx
unitcellengine/geometry/definitions/Hex prism diamond.ltcx
unitcellengine/geometry/definitions/Hex prism edge.ltcx
unitcellengine/geometry/definitions/Hex prism laves phase.ltcx
unitcellengine/geometry/definitions/Hex prism vertex centroid.ltcx
unitcellengine/geometry/definitions/Hexagonal honeycomb.ltcx
unitcellengine/geometry/definitions/IsoTruss.ltcx
unitcellengine/geometry/definitions/Kelvin cell.ltcx
unitcellengine/geometry/definitions/Oct vertex centroid.ltcx
unitcellengine/geometry/definitions/Octet.ltcx
unitcellengine/geometry/definitions/Re-entrant honeycomb.ltcx
unitcellengine/geometry/definitions/Re-entrant.ltcx
unitcellengine/geometry/definitions/Simple cubic foam.ltcx
unitcellengine/geometry/definitions/Simple cubic.ltcx
unitcellengine/geometry/definitions/Square honeycomb rotated.ltcx
unitcellengine/geometry/definitions/Square honeycomb.ltcx
unitcellengine/geometry/definitions/Tet oct vertex centroid.ltcx
unitcellengine/geometry/definitions/Triangular honeycomb rotated.ltcx
unitcellengine/geometry/definitions/Triangular honeycomb.ltcx
unitcellengine-0.0.12.dist-info/METADATA
unitcellengine-0.0.12.dist-info/WHEEL
unitcellengine-0.0.12.dist-info/licenses/LICENSE
unitcellengine-0.0.12.dist-info/RECORD
