Metadata-Version: 2.4
Name: unitcellengine
Version: 0.0.12
Summary: Lattice unitcell geometry and analysis framework
Project-URL: Homepage, https://github.com/unitcellhub/unitcellengine
Project-URL: Bug Reports, https://github.com/unitcellhub/unitcellengine/issues
Author-email: Ryan Watkins <watkinrt@gmail.com>
License:                                  Apache License
License-File: LICENSE
Keywords: finite element,homogenization,lattice,unitcell,unitcellhub
Classifier: Development Status :: 3 - Alpha
Requires-Python: <3.12,>=3.10
Requires-Dist: dill>=0.3.9
Requires-Dist: gmsh>=4.13.1
Requires-Dist: mkl-service>=2.4.1
Requires-Dist: numba>=0.60.0
Requires-Dist: numpy<2.0
Requires-Dist: pandas>=2.2.3
Requires-Dist: plotly>=5.24.1
Requires-Dist: pyamg>=5.2.1
Requires-Dist: pypardiso>=0.4.6
Requires-Dist: pyvista>=0.44.1
Requires-Dist: scikit-image>=0.24.0
Requires-Dist: scipy>=1.14.1
Requires-Dist: tables>=3.10.1
Requires-Dist: trimesh>=4.5.1
Requires-Dist: unitcellsdf>=0.0.2
Requires-Dist: vtk>=9.3.1
